qqqfome/__init__.py
qqqfome/backend.py
qqqfome/common.py
qqqfome/config.json
qqqfome/daemon.py
qqqfome/db.py
qqqfome/entry.py
qqqfome/strings.py
qqqfome/test/__init__.py
qqqfome/test/common.py
qqqfome/test/test_common.py
qqqfome/test/test_db.py
qqqfome-0.0.4.dist-info/DESCRIPTION.rst
qqqfome-0.0.4.dist-info/METADATA
qqqfome-0.0.4.dist-info/RECORD
qqqfome-0.0.4.dist-info/WHEEL
qqqfome-0.0.4.dist-info/entry_points.txt
qqqfome-0.0.4.dist-info/metadata.json
qqqfome-0.0.4.dist-info/top_level.txt
