Metadata-Version: 2.0
Name: qqqfome
Version: 0.0.4
Summary: I'm a daemon server that auto send message to your zhihu new followers.
Home-page: https://github.com/7sDream/qqqfome
Author: 7sDream
Author-email: didislover@gmail.com
License: MIT
Keywords: internet,daemon,sqlite
Platform: UNKNOWN
Classifier: Development Status :: 3 - Alpha
Classifier: Environment :: No Input/Output (Daemon)
Classifier: Environment :: Web Environment
Classifier: License :: OSI Approved :: MIT License
Classifier: Natural Language :: English
Classifier: Operating System :: OS Independent
Classifier: Programming Language :: Python :: 3
Classifier: Topic :: Database
Classifier: Topic :: Internet :: WWW/HTTP
Requires-Dist: zhihu-py3
